{
  "experiment": "distillation",
  "timestamp": "2026-04-09T07:34:09.982975",
  "note": "Auto-generated during surrogate_ft",
  "dataset": "cifar10",
  "label_mode": "soft",
  "teacher": {
    "name": "resnet20",
    "num_parameters": 272474,
    "num_parameters_human": "272,474",
    "accuracy": 0.9259
  },
  "student": {
    "architecture": "resnet20"
  },
  "watermark_config": {
    "r_w": 0.05,
    "r_w_percent": "5.0%",
    "delta_logit": 2.0,
    "beta": 0.5,
    "num_classes": 10,
    "method": "logit_space_confidence_shift",
    "verification": "wilcoxon_signed_rank_paired",
    "verify_temperature": 5.0
  },
  "distillation_config": {
    "temperature": 5,
    "n_queries": 50000,
    "epochs": 80,
    "lr": 0.002,
    "batch_size": 128,
    "label_mode": "soft"
  },
  "result": {
    "temperature": 5,
    "student_accuracy": 0.8428,
    "n_triggers": 2492,
    "confidence_shift": 0.000113,
    "mean_trigger_conf": 0.050808,
    "mean_control_conf": 0.050696,
    "n_trigger": 2492,
    "n_control": 2492,
    "test": "wilcoxon_signed_rank",
    "statistic": 1416968.0,
    "p_value": 0.9999248965077497,
    "log10_p_value": -0.0,
    "verified": false,
    "verify_temperature": 5.0,
    "trigger_source": "rec_trigger",
    "all_designs": {
      "single_ctrl": {
        "verified": false,
        "p_value": 0.9999248965077497,
        "log10_p_value": -0.0,
        "test": "wilcoxon_signed_rank",
        "statistic": 1416968.0,
        "control_design": "single_ctrl",
        "mean_trigger_conf": 0.050808,
        "mean_control_conf": 0.050696,
        "confidence_shift": 0.000113,
        "median_shift": -0.001847,
        "n_trigger": 2492,
        "n_control": 2492,
        "n_pairs": 2492,
        "eta": 5.421010862427522e-20,
        "verify_temperature": 5.0
      },
      "mean_rest": {
        "verified": false,
        "p_value": 1.0,
        "log10_p_value": 0.0,
        "test": "wilcoxon_signed_rank",
        "statistic": 1179291.0,
        "control_design": "mean_rest",
        "mean_trigger_conf": 0.050808,
        "mean_control_conf": 0.049565,
        "confidence_shift": 0.001244,
        "median_shift": -0.004414,
        "n_trigger": 2492,
        "n_control": 2492,
        "n_pairs": 2492,
        "eta": 5.421010862427522e-20,
        "verify_temperature": 5.0
      },
      "suspect_top1": {
        "verified": false,
        "p_value": 0.9999531419300237,
        "log10_p_value": -0.0,
        "test": "wilcoxon_signed_rank",
        "statistic": 1412816.0,
        "control_design": "suspect_top1",
        "mean_trigger_conf": 0.05067,
        "mean_control_conf": 0.050672,
        "confidence_shift": -2e-06,
        "median_shift": -0.00185,
        "n_trigger": 2492,
        "n_control": 2492,
        "n_pairs": 2492,
        "eta": 5.421010862427522e-20,
        "verify_temperature": 5.0
      }
    }
  }
}